lumix/__init__.py
lumix/agent/__init__.py
lumix/agent/tool_calls/__init__.py
lumix/agent/tool_calls/agent.py
lumix/agent/tool_calls/register.py
lumix/agent/tool_calls/tools.py
lumix/agent/tools/__init__.py
lumix/agent/tools/tools.py
lumix/agent/tools/search/__init__.py
lumix/agent/tools/search/baidu.py
lumix/agent/tools/search/baidu_image.py
lumix/agent/tools/search/bing.py
lumix/agent/tools/search/config/__init__.py
lumix/agent/tools/search/config/baidu.py
lumix/api/__init__.py
lumix/api/openai.py
lumix/documents/__init__.py
lumix/documents/load_md.py
lumix/documents/read/__init__.py
lumix/documents/read/pdf.py
lumix/embedding/__init__.py
lumix/embedding/base.py
lumix/embedding/openai.py
lumix/embedding/pretrained.py
lumix/executor/__init__.py
lumix/executor/retry.py
lumix/llm/__init__.py
lumix/llm/completion/__init__.py
lumix/llm/completion/openai.py
lumix/mcp/__init__.py
lumix/mcp/client.py
lumix/prompt/__init__.py
lumix/prompt/messages.py
lumix/prompt/template.py
lumix/prompt/prompts/__init__.py
lumix/prompt/prompts/extract_table.py
lumix/prompt/prompts/graph_rag.py
lumix/prompt/prompts/image.py
lumix/structured/__init__.py
lumix/structured/parse.py
lumix/types/__init__.py
lumix/types/documents/__init__.py
lumix/types/documents/documents.py
lumix/types/documents/markdown.py
lumix/types/embedding/__init__.py
lumix/types/embedding/embedding.py
lumix/types/messages/__init__.py
lumix/types/messages/base.py
lumix/types/messages/content.py
lumix/types/messages/image.py
lumix/types/messages/tool.py
lumix/types/openai/__init__.py
lumix/types/openai/literal.py
lumix/types/openai/sse.py
lumix/types/openai/sync.py
lumix/types/task/__init__.py
lumix/types/tools/__init__.py
lumix/types/tools/tools.py
lumix/utils/__init__.py
lumix/utils/config.py
lumix/utils/image.py
lumix/utils/logger.py
lumix/utils/utils.py
lumix/utils/completion/__init__.py
lumix/utils/completion/chunk.py
lumix/utils/completion/completion.py
lumix/utils/completion/sync.py
lumix/utils/string/__init__.py
lumix-0.0.7.dist-info/METADATA
lumix-0.0.7.dist-info/WHEEL
lumix-0.0.7.dist-info/RECORD
