Metadata-Version: 2.4
Name: lumix
Version: 0.0.7
Summary: A llm Python package.
Author-email: chensy cao <chensy.cao@foxmail.com>
Maintainer-email: chensy cao <chensy.cao@foxmail.com>
License: MIT
Keywords: Agent,LLM
Classifier: License :: OSI Approved :: MIT License
Classifier: Operating System :: OS Independent
Classifier: Programming Language :: Python :: 3.9
Classifier: Programming Language :: Python :: 3.10
Classifier: Programming Language :: Python :: 3.11
Classifier: Programming Language :: Python :: 3.12
Classifier: Programming Language :: Python :: 3.13
Classifier: Topic :: Software Development :: Libraries
Classifier: Topic :: Software Development :: Libraries :: Python Modules
Requires-Python: >=3.10
Requires-Dist: black>=24.10.0
Requires-Dist: bs4>=0.0.2
Requires-Dist: chardet>=5.2.0
Requires-Dist: colorama>=0.4.6
Requires-Dist: langchain-text-splitters>=0.3.7
Requires-Dist: numpy>=1.23.5
Requires-Dist: openpyxl>=3.1.5
Requires-Dist: pandas>=1.0
Requires-Dist: pydantic>=2.8.2
Requires-Dist: pymupdf>=1.25.4
Requires-Dist: requests>=2.32.3
Requires-Dist: scikit-image>=0.25.2
Requires-Dist: tqdm>=4.65.0
Provides-Extra: mkdocs
Requires-Dist: mkdocs-git-authors-plugin>=0.9.0; extra == 'mkdocs'
Requires-Dist: mkdocs-git-committers-plugin-2>=2.4.1; extra == 'mkdocs'
Requires-Dist: mkdocs-git-revision-date-localized-plugin>=1.3.0; extra == 'mkdocs'
Requires-Dist: mkdocs-glightbox>=0.4.0; extra == 'mkdocs'
Requires-Dist: mkdocs-material>=9.5.42; extra == 'mkdocs'
Requires-Dist: mkdocs-minify-plugin>=0.8.0; extra == 'mkdocs'
Requires-Dist: mkdocs-rss-plugin>=1.15.0; extra == 'mkdocs'
Requires-Dist: mkdocstrings>=0.26.2; extra == 'mkdocs'
